chacon/__init__.py
chacon/classes.py
chacon/utils.py
tests/__init__.py
tests/test_integration.py
chacon-0.0a0.dev0.dist-info/LICENSE
chacon-0.0a0.dev0.dist-info/METADATA
chacon-0.0a0.dev0.dist-info/WHEEL
chacon-0.0a0.dev0.dist-info/entry_points.txt
chacon-0.0a0.dev0.dist-info/top_level.txt
chacon-0.0a0.dev0.dist-info/RECORD
